{"autoplayTransitionDelay":5,"author":"","timestamp":"2019-28-30 17:7:0","loopSlideshow":0,"filename":"名称未設定.key","autoplayBuildDelay":2,"comment":"","title":"名称未設定.key","showMode":0,"creator":"Apple Keynote 8.3","slideList":["91463CD8-F678-439C-B106-40E63584BF91"],"soundtrack":{"mode":0,"volume":1},"slideWidth":1024,"slideHeight":768,"slideCount":1,"majorVersion":1,"minorVersion":2,"fonts":["GillSans","HiraKakuProN-W3","AvenirNext-Medium","DINCondensed-Bold","AvenirNext-DemiBold","DINAlternate-Bold"]}